{"_path":"/backend_en","_dir":"","_draft":false,"_partial":false,"_locale":"","_empty":false,"title":"BackendEn","description":"","body":{"type":"root","children":[{"type":"element","tag":"code","props":{"code":"{\r\n  \"stacksBackend\": [\r\n    {\r\n      \"name\": \"Node.js\",\r\n      \"description\": \"Node.js is an asynchronous JavaScript runtime for building scalable network applications.\",\r\n      \"website\": \"https://nodejs.org/\"\r\n    },\r\n    {\r\n      \"name\": \"LUA\",\r\n      \"description\": \"LUA is a lightweight, high-performance scripting language used in embedded applications, games, and real-time systems.\",\r\n      \"website\": \"https://www.lua.org/\"\r\n    },\r\n    {\r\n      \"name\": \"AdonisJS\",\r\n      \"description\": \"AdonisJS is a web framework for Node.js that provides a solid foundation for building robust and scalable web applications.\",\r\n      \"website\": \"https://adonisjs.com/\"\r\n    },\r\n    {\r\n      \"name\": \"MySQL\",\r\n      \"description\": \"MySQL is an open-source relational database management system widely used for its performance, reliability, and ease of use.\",\r\n      \"website\": \"https://www.mysql.com/\"\r\n    }\r\n  ]\r\n}\n","language":"json","meta":null},"children":[{"type":"element","tag":"pre","props":{},"children":[{"type":"element","tag":"code","props":{"__ignoreMap":""},"children":[{"type":"element","tag":"span","props":{"class":"line","line":1},"children":[{"type":"element","tag":"span","props":{"class":"ct-da16cf"},"children":[{"type":"text","value":"{\n"}]}]},{"type":"element","tag":"span","props":{"class":"line","line":2},"children":[{"type":"element","tag":"span","props":{"class":"ct-da16cf"},"children":[{"type":"text","value":"  "}]},{"type":"element","tag":"span","props":{"class":"ct-7cfdeb"},"children":[{"type":"text","value":"\"stacksBackend\""}]},{"type":"element","tag":"span","props":{"class":"ct-da16cf"},"children":[{"type":"text","value":": [\n"}]}]},{"type":"element","tag":"span","props":{"class":"line","line":3},"children":[{"type":"element","tag":"span","props":{"class":"ct-da16cf"},"children":[{"type":"text","value":"    {\n"}]}]},{"type":"element","tag":"span","props":{"class":"line","line":4},"children":[{"type":"element","tag":"span","props":{"class":"ct-da16cf"},"children":[{"type":"text","value":"      "}]},{"type":"element","tag":"span","props":{"class":"ct-7cfdeb"},"children":[{"type":"text","value":"\"name\""}]},{"type":"element","tag":"span","props":{"class":"ct-da16cf"},"children":[{"type":"text","value":": "}]},{"type":"element","tag":"span","props":{"class":"ct-7cb3d1"},"children":[{"type":"text","value":"\"Node.js\""}]},{"type":"element","tag":"span","props":{"class":"ct-da16cf"},"children":[{"type":"text","value":",\n"}]}]},{"type":"element","tag":"span","props":{"class":"line","line":5},"children":[{"type":"element","tag":"span","props":{"class":"ct-da16cf"},"children":[{"type":"text","value":"      "}]},{"type":"element","tag":"span","props":{"class":"ct-7cfdeb"},"children":[{"type":"text","value":"\"description\""}]},{"type":"element","tag":"span","props":{"class":"ct-da16cf"},"children":[{"type":"text","value":": "}]},{"type":"element","tag":"span","props":{"class":"ct-7cb3d1"},"children":[{"type":"text","value":"\"Node.js is an asynchronous JavaScript runtime for building scalable network applications.\""}]},{"type":"element","tag":"span","props":{"class":"ct-da16cf"},"children":[{"type":"text","value":",\n"}]}]},{"type":"element","tag":"span","props":{"class":"line","line":6},"children":[{"type":"element","tag":"span","props":{"class":"ct-da16cf"},"children":[{"type":"text","value":"      "}]},{"type":"element","tag":"span","props":{"class":"ct-7cfdeb"},"children":[{"type":"text","value":"\"website\""}]},{"type":"element","tag":"span","props":{"class":"ct-da16cf"},"children":[{"type":"text","value":": "}]},{"type":"element","tag":"span","props":{"class":"ct-7cb3d1"},"children":[{"type":"text","value":"\"https://nodejs.org/\"\n"}]}]},{"type":"element","tag":"span","props":{"class":"line","line":7},"children":[{"type":"element","tag":"span","props":{"class":"ct-da16cf"},"children":[{"type":"text","value":"    },\n"}]}]},{"type":"element","tag":"span","props":{"class":"line","line":8},"children":[{"type":"element","tag":"span","props":{"class":"ct-da16cf"},"children":[{"type":"text","value":"    {\n"}]}]},{"type":"element","tag":"span","props":{"class":"line","line":9},"children":[{"type":"element","tag":"span","props":{"class":"ct-da16cf"},"children":[{"type":"text","value":"      "}]},{"type":"element","tag":"span","props":{"class":"ct-7cfdeb"},"children":[{"type":"text","value":"\"name\""}]},{"type":"element","tag":"span","props":{"class":"ct-da16cf"},"children":[{"type":"text","value":": "}]},{"type":"element","tag":"span","props":{"class":"ct-7cb3d1"},"children":[{"type":"text","value":"\"LUA\""}]},{"type":"element","tag":"span","props":{"class":"ct-da16cf"},"children":[{"type":"text","value":",\n"}]}]},{"type":"element","tag":"span","props":{"class":"line","line":10},"children":[{"type":"element","tag":"span","props":{"class":"ct-da16cf"},"children":[{"type":"text","value":"      "}]},{"type":"element","tag":"span","props":{"class":"ct-7cfdeb"},"children":[{"type":"text","value":"\"description\""}]},{"type":"element","tag":"span","props":{"class":"ct-da16cf"},"children":[{"type":"text","value":": "}]},{"type":"element","tag":"span","props":{"class":"ct-7cb3d1"},"children":[{"type":"text","value":"\"LUA is a lightweight, high-performance scripting language used in embedded applications, games, and real-time systems.\""}]},{"type":"element","tag":"span","props":{"class":"ct-da16cf"},"children":[{"type":"text","value":",\n"}]}]},{"type":"element","tag":"span","props":{"class":"line","line":11},"children":[{"type":"element","tag":"span","props":{"class":"ct-da16cf"},"children":[{"type":"text","value":"      "}]},{"type":"element","tag":"span","props":{"class":"ct-7cfdeb"},"children":[{"type":"text","value":"\"website\""}]},{"type":"element","tag":"span","props":{"class":"ct-da16cf"},"children":[{"type":"text","value":": "}]},{"type":"element","tag":"span","props":{"class":"ct-7cb3d1"},"children":[{"type":"text","value":"\"https://www.lua.org/\"\n"}]}]},{"type":"element","tag":"span","props":{"class":"line","line":12},"children":[{"type":"element","tag":"span","props":{"class":"ct-da16cf"},"children":[{"type":"text","value":"    },\n"}]}]},{"type":"element","tag":"span","props":{"class":"line","line":13},"children":[{"type":"element","tag":"span","props":{"class":"ct-da16cf"},"children":[{"type":"text","value":"    {\n"}]}]},{"type":"element","tag":"span","props":{"class":"line","line":14},"children":[{"type":"element","tag":"span","props":{"class":"ct-da16cf"},"children":[{"type":"text","value":"      "}]},{"type":"element","tag":"span","props":{"class":"ct-7cfdeb"},"children":[{"type":"text","value":"\"name\""}]},{"type":"element","tag":"span","props":{"class":"ct-da16cf"},"children":[{"type":"text","value":": "}]},{"type":"element","tag":"span","props":{"class":"ct-7cb3d1"},"children":[{"type":"text","value":"\"AdonisJS\""}]},{"type":"element","tag":"span","props":{"class":"ct-da16cf"},"children":[{"type":"text","value":",\n"}]}]},{"type":"element","tag":"span","props":{"class":"line","line":15},"children":[{"type":"element","tag":"span","props":{"class":"ct-da16cf"},"children":[{"type":"text","value":"      "}]},{"type":"element","tag":"span","props":{"class":"ct-7cfdeb"},"children":[{"type":"text","value":"\"description\""}]},{"type":"element","tag":"span","props":{"class":"ct-da16cf"},"children":[{"type":"text","value":": "}]},{"type":"element","tag":"span","props":{"class":"ct-7cb3d1"},"children":[{"type":"text","value":"\"AdonisJS is a web framework for Node.js that provides a solid foundation for building robust and scalable web applications.\""}]},{"type":"element","tag":"span","props":{"class":"ct-da16cf"},"children":[{"type":"text","value":",\n"}]}]},{"type":"element","tag":"span","props":{"class":"line","line":16},"children":[{"type":"element","tag":"span","props":{"class":"ct-da16cf"},"children":[{"type":"text","value":"      "}]},{"type":"element","tag":"span","props":{"class":"ct-7cfdeb"},"children":[{"type":"text","value":"\"website\""}]},{"type":"element","tag":"span","props":{"class":"ct-da16cf"},"children":[{"type":"text","value":": "}]},{"type":"element","tag":"span","props":{"class":"ct-7cb3d1"},"children":[{"type":"text","value":"\"https://adonisjs.com/\"\n"}]}]},{"type":"element","tag":"span","props":{"class":"line","line":17},"children":[{"type":"element","tag":"span","props":{"class":"ct-da16cf"},"children":[{"type":"text","value":"    },\n"}]}]},{"type":"element","tag":"span","props":{"class":"line","line":18},"children":[{"type":"element","tag":"span","props":{"class":"ct-da16cf"},"children":[{"type":"text","value":"    {\n"}]}]},{"type":"element","tag":"span","props":{"class":"line","line":19},"children":[{"type":"element","tag":"span","props":{"class":"ct-da16cf"},"children":[{"type":"text","value":"      "}]},{"type":"element","tag":"span","props":{"class":"ct-7cfdeb"},"children":[{"type":"text","value":"\"name\""}]},{"type":"element","tag":"span","props":{"class":"ct-da16cf"},"children":[{"type":"text","value":": "}]},{"type":"element","tag":"span","props":{"class":"ct-7cb3d1"},"children":[{"type":"text","value":"\"MySQL\""}]},{"type":"element","tag":"span","props":{"class":"ct-da16cf"},"children":[{"type":"text","value":",\n"}]}]},{"type":"element","tag":"span","props":{"class":"line","line":20},"children":[{"type":"element","tag":"span","props":{"class":"ct-da16cf"},"children":[{"type":"text","value":"      "}]},{"type":"element","tag":"span","props":{"class":"ct-7cfdeb"},"children":[{"type":"text","value":"\"description\""}]},{"type":"element","tag":"span","props":{"class":"ct-da16cf"},"children":[{"type":"text","value":": "}]},{"type":"element","tag":"span","props":{"class":"ct-7cb3d1"},"children":[{"type":"text","value":"\"MySQL is an open-source relational database management system widely used for its performance, reliability, and ease of use.\""}]},{"type":"element","tag":"span","props":{"class":"ct-da16cf"},"children":[{"type":"text","value":",\n"}]}]},{"type":"element","tag":"span","props":{"class":"line","line":21},"children":[{"type":"element","tag":"span","props":{"class":"ct-da16cf"},"children":[{"type":"text","value":"      "}]},{"type":"element","tag":"span","props":{"class":"ct-7cfdeb"},"children":[{"type":"text","value":"\"website\""}]},{"type":"element","tag":"span","props":{"class":"ct-da16cf"},"children":[{"type":"text","value":": "}]},{"type":"element","tag":"span","props":{"class":"ct-7cb3d1"},"children":[{"type":"text","value":"\"https://www.mysql.com/\"\n"}]}]},{"type":"element","tag":"span","props":{"class":"line","line":22},"children":[{"type":"element","tag":"span","props":{"class":"ct-da16cf"},"children":[{"type":"text","value":"    }\n"}]}]},{"type":"element","tag":"span","props":{"class":"line","line":23},"children":[{"type":"element","tag":"span","props":{"class":"ct-da16cf"},"children":[{"type":"text","value":"  ]\n"}]}]},{"type":"element","tag":"span","props":{"class":"line","line":24},"children":[{"type":"element","tag":"span","props":{"class":"ct-da16cf"},"children":[{"type":"text","value":"}"}]}]}]}]}]},{"type":"element","tag":"style","children":[{"type":"text","value":".ct-7cb3d1{color:#A5D6FF}\n.ct-7cfdeb{color:#7EE787}\n.ct-da16cf{color:#C9D1D9}"}]}],"toc":{"title":"","searchDepth":2,"depth":2,"links":[]}},"_type":"markdown","_id":"content:backend_en.md","_source":"content","_file":"backend_en.md","_extension":"md"}